open_magvit2/__init__.py
open_magvit2/combine_npz.py
open_magvit2/evaluation.py
open_magvit2/generate.py
open_magvit2/main.py
open_magvit2/reconstruct.py
open_magvit2/sample.py
open_magvit2/configs/__init__.py
open_magvit2/configs/gpu/imagenet_conditional_llama_B.yaml
open_magvit2/configs/gpu/imagenet_conditional_llama_L.yaml
open_magvit2/configs/gpu/imagenet_conditional_llama_XL.yaml
open_magvit2/configs/gpu/imagenet_lfqgan_128_L.yaml
open_magvit2/configs/gpu/imagenet_lfqgan_256_L.yaml
open_magvit2/configs/npu/imagenet_conditional_llama_B.yaml
open_magvit2/configs/npu/imagenet_conditional_llama_L.yaml
open_magvit2/configs/npu/imagenet_conditional_llama_XL.yaml
open_magvit2/configs/npu/imagenet_lfqgan_128_L.yaml
open_magvit2/configs/npu/imagenet_lfqgan_256_L.yaml
open_magvit2/metrics/__init__.py
open_magvit2/metrics/fid.py
open_magvit2/metrics/inception.py
open_magvit2/taming/__init__.py
open_magvit2/taming/lr_scheduler.py
open_magvit2/taming/util.py
open_magvit2/taming/models/__init__.py
open_magvit2/taming/models/cond_transformer_gpt.py
open_magvit2/taming/models/dummy_cond_stage.py
open_magvit2/taming/models/lfqgan.py
open_magvit2/taming/modules/__init__.py
open_magvit2/taming/modules/ema.py
open_magvit2/taming/modules/util.py
open_magvit2/taming/modules/diffusionmodules/__init__.py
open_magvit2/taming/modules/diffusionmodules/improved_model.py
open_magvit2/taming/modules/diffusionmodules/model.py
open_magvit2/taming/modules/discriminator/__init__.py
open_magvit2/taming/modules/discriminator/model.py
open_magvit2/taming/modules/losses/__init__.py
open_magvit2/taming/modules/losses/lpips.py
open_magvit2/taming/modules/losses/segmentation.py
open_magvit2/taming/modules/losses/vqperceptual.py
open_magvit2/taming/modules/scheduler/__init__.py
open_magvit2/taming/modules/scheduler/lr_scheduler.py
open_magvit2/taming/modules/transformer/__init__.py
open_magvit2/taming/modules/transformer/gpt.py
open_magvit2/taming/modules/transformer/permuter.py
open_magvit2-1.1.dist-info/LICENSE
open_magvit2-1.1.dist-info/METADATA
open_magvit2-1.1.dist-info/WHEEL
open_magvit2-1.1.dist-info/top_level.txt
open_magvit2-1.1.dist-info/RECORD
